[
  {
    "id": 1,
    "title": "Star Wars",
    "released": 1977,
    "rating": "PG",
    "director": "George Lucas",
    "description": "Luke Skywalker, a spirited farm boy, joins rebel forces to save Princess Leia from the evil Darth Vader, and the galaxy from the Empire's planet-destroying Death Star.",
    "imdb": "tt0076759",
    "genres": [
      "Action",
      "Adventure",
      "Sci-Fi"
    ]
  },

  {
    "id": 2,
    "title": "Star Wars: Episode V - The Empire Strikes Back",
    "released": 1980,
    "rating": "PG",
    "director": "Irvin Kershner",
    "description": "As Luke trains with Master Yoda to become a Jedi Knight, his friends evade the Imperial fleet under the command of Darth Vader who is obsessed with turning Skywalker to the Dark Side of the Force.",
    "imdb": "tt0080684",
    "genres": [
      "Action",
      "Adventure",
      "Sci-Fi"
    ]
  },

  {
    "id": 3,
    "title": "Star Wars: Episode VI - Return of the Jedi",
    "released": 1983,
    "rating": "PG",
    "director": "Richard Marquand",
    "description": "After rescuing Han Solo from the palace of Jabba the Hutt, the Rebels attempt to destroy the Second Death Star, while Luke Skywalker tries to bring his father back to the Light Side of the Force.",
    "imdb": "tt0086190",
    "genres": [
      "Action",
      "Adventure",
      "Sci-Fi"
    ]
  }
]